aiogram_calendar/__init__.py
aiogram_calendar/common.py
aiogram_calendar/dialog_calendar.py
aiogram_calendar/schemas.py
aiogram_calendar/simple_calendar.py
aiogram_calendar/tests/__init__.py
aiogram_calendar/tests/test_dialog_calendar.py
aiogram_calendar/tests/test_simple_calendar.py
aiogram_calendar-0.5.0.dist-info/LICENSE.txt
aiogram_calendar-0.5.0.dist-info/METADATA
aiogram_calendar-0.5.0.dist-info/WHEEL
aiogram_calendar-0.5.0.dist-info/top_level.txt
aiogram_calendar-0.5.0.dist-info/RECORD
