Metadata-Version: 2.1
Name: aiogram-calendar
Version: 0.5.0
Summary: Simple Inline Calendar & Date Selection tool for Aiogram Telegram bots
Author-email: Andrii Nikolabai <nikolabay.as@gmail.com>
License: MIT License
Project-URL: Homepage, https://github.com/noXplode/aiogram_calendar
Keywords: Aiogram,Telegram,Bots,Calendar
Classifier: Development Status :: 3 - Alpha
Classifier: Intended Audience :: Developers
Classifier: Topic :: Software Development :: Libraries :: Python Modules
Classifier: License :: OSI Approved :: MIT License
Classifier: Programming Language :: Python :: 3
Classifier: Programming Language :: Python :: 3.8
Classifier: Programming Language :: Python :: 3.9
Classifier: Programming Language :: Python :: 3.10
Classifier: Programming Language :: Python :: 3.11
Classifier: Programming Language :: Python :: 3.12
Requires-Python: >=3.8
License-File: LICENSE.txt
Requires-Dist: aiogram>=3
Provides-Extra: dev
Requires-Dist: pytest; extra == "dev"
Requires-Dist: pytest-asyncio; extra == "dev"
